webquest/__init__.py
webquest/browsers/__init__.py
webquest/browsers/browser.py
webquest/browsers/hyperbrowser.py
webquest/parsers/__init__.py
webquest/parsers/openai_parser.py
webquest/py.typed
webquest/scrapers/__init__.py
webquest/scrapers/any_article/__init__.py
webquest/scrapers/any_article/request.py
webquest/scrapers/any_article/response.py
webquest/scrapers/any_article/scraper.py
webquest/scrapers/any_article/settings.py
webquest/scrapers/duckduckgo_search/__init__.py
webquest/scrapers/duckduckgo_search/request.py
webquest/scrapers/duckduckgo_search/response.py
webquest/scrapers/duckduckgo_search/scraper.py
webquest/scrapers/duckduckgo_search/settings.py
webquest/scrapers/google_news_search/__init__.py
webquest/scrapers/google_news_search/request.py
webquest/scrapers/google_news_search/response.py
webquest/scrapers/google_news_search/scraper.py
webquest/scrapers/google_news_search/settings.py
webquest/scrapers/scraper.py
webquest/scrapers/youtube_search/__init__.py
webquest/scrapers/youtube_search/request.py
webquest/scrapers/youtube_search/response.py
webquest/scrapers/youtube_search/scraper.py
webquest/scrapers/youtube_search/settings.py
webquest/scrapers/youtube_transcript/__init__.py
webquest/scrapers/youtube_transcript/request.py
webquest/scrapers/youtube_transcript/response.py
webquest/scrapers/youtube_transcript/scraper.py
webquest/scrapers/youtube_transcript/settings.py
webquest-0.12.7.dist-info/WHEEL
webquest-0.12.7.dist-info/METADATA
webquest-0.12.7.dist-info/RECORD
