Metadata-Version: 2.4
Name: webquest
Version: 0.12.7
Summary: WebQuest is an extensible Python toolkit for high-level web scraping, built around a generic Playwright-based scraper interface for quickly building, running, and reusing custom scrapers.
License-Expression: Apache-2.0
Requires-Dist: beautifulsoup4>=4.14.2
Requires-Dist: hyperbrowser>=0.68.0
Requires-Dist: openai>=2.6.0
Requires-Dist: playwright>=1.55.0
Requires-Dist: pydantic>=2.12.3
Requires-Dist: pydantic-settings>=2.12.0
Requires-Python: >=3.12
Project-URL: Documentation, https://mustafametesengul.github.io/webquest/
Project-URL: Source, https://github.com/mustafametesengul/webquest
